GENetLib/BsplineFunc.py
GENetLib/GE_Net.py
GENetLib/__init__.py
GENetLib/fda_func.py
GENetLib/func_ge.py
GENetLib/grid_func_ge.py
GENetLib/grid_scalar_ge.py
GENetLib/plot_gene.py
GENetLib/pre_data.py
GENetLib/predict_ge.py
GENetLib/scalar_ge.py
GENetLib/scalar_l2train.py
GENetLib/scalar_mcp_l2train.py
GENetLib/sim_data.py
GENetLib/survival_costfunc_cindex.py
genetlib-1.2.7.dist-info/licenses/LICENSE
genetlib-1.2.7.dist-info/METADATA
genetlib-1.2.7.dist-info/WHEEL
genetlib-1.2.7.dist-info/top_level.txt
genetlib-1.2.7.dist-info/RECORD
